{"cameraMode":{"drawMode":0,"name":"Shaded","section":"Shading Mode"},"sceneLighting":true,"audioPlay":false,"sceneViewState":{"m_AlwaysRefresh":false,"showFog":true,"showSkybox":true,"showFlares":true,"showImageEffects":true,"showParticleSystems":true,"showVisualEffectGraphs":true,"m_FxEnabled":true},"in2DMode":false,"pivot":{"x":-6.256288051605225,"y":-2.81260085105896,"z":1.0788580179214478},"rotation":{"x":0.11316987127065659,"y":-0.16414892673492433,"z":0.018967049196362497,"w":0.979752779006958},"size":10.42953872680664,"orthographic":false}